{
  "project_info": {
    "project_number": "816152989290",
    "firebase_url": "https://easyway-cms-default-rtdb.europe-west1.firebasedatabase.app",
    "project_id": "easyway-cms",
    "storage_bucket": "easyway-cms.appspot.com"
  },
  "client": [
    {
      "client_info": {
        "mobilesdk_app_id": "1:816152989290:android:d3f2e99e54b3746120c413",
        "android_client_info": {
          "package_name": "com.example.case_management_tool"
        }
      },
      "oauth_client": [],
      "api_key": [
        {
          "current_key": "AIzaSyAHQ8YRtmOzvDuTIZ6ZarzcUZWEM9Bsa-w"
        }
      ],
      "services": {
        "appinvite_service": {
          "other_platform_oauth_client": []
        }
      }
    }
  ],
  "configuration_version": "1"
}